bubbleprint/__init__.py
bubbleprint-0.0.1.dist-info/LICENSE
bubbleprint-0.0.1.dist-info/METADATA
bubbleprint-0.0.1.dist-info/WHEEL
bubbleprint-0.0.1.dist-info/top_level.txt
bubbleprint-0.0.1.dist-info/RECORD
