Metadata-Version: 2.1
Name: bubbleprint
Version: 0.0.1
Summary: Give your print statements personality
Home-page: UNKNOWN
Author: Brian K. Blaylock
Author-email: blaylockbk@gmail.com
License: MIT
Project-URL: Source Code, https://github.com/blaylockbk/BubblePrint
Keywords: python,print
Platform: UNKNOWN
Classifier: Programming Language :: Python
Requires-Python: >=3.8
